sug/__init__.py
sug/__main__.py
sug-0.1.1.dist-info/entry_points.txt
sug-0.1.1.dist-info/COPYING
sug-0.1.1.dist-info/WHEEL
sug-0.1.1.dist-info/METADATA
sug-0.1.1.dist-info/RECORD
